<?xml version="1.0" encoding="UTF-8"?>
<spirit:component xmlns:xilinx="http://www.xilinx.com" xmlns:spirit="http://www.spiritconsortium.org/XMLSchema/SPIRIT/1685-2009" xmlns:xsi="http://www.w3.org/2001/XMLSchema-instance">
  <spirit:vendor>xilinx.com</spirit:vendor>
  <spirit:library>ip</spirit:library>
  <spirit:name>shell_ert_subsystem</spirit:name>
  <spirit:version>2.0</spirit:version>
  <spirit:model>
    <spirit:views>
      <spirit:view>
        <spirit:name>xilinx_blockdiagram</spirit:name>
        <spirit:displayName>Block Diagram</spirit:displayName>
        <spirit:envIdentifier>:vivado.xilinx.com:block.diagram</spirit:envIdentifier>
        <spirit:fileSetRef>
          <spirit:localName>xilinx_blockdiagram_view_fileset</spirit:localName>
        </spirit:fileSetRef>
        <spirit:parameters>
          <spirit:parameter>
            <spirit:name>viewChecksum</spirit:name>
            <spirit:value>7d9f514c</spirit:value>
          </spirit:parameter>
        </spirit:parameters>
      </spirit:view>
      <spirit:view>
        <spirit:name>xilinx_elaboratebd</spirit:name>
        <spirit:displayName>Elaborate BD</spirit:displayName>
        <spirit:envIdentifier>:vivado.xilinx.com:elaborate.bd</spirit:envIdentifier>
        <spirit:fileSetRef>
          <spirit:localName>xilinx_elaboratebd_xilinx_com_ip_axi_protocol_converter_2_1__ref_view_fileset</spirit:localName>
        </spirit:fileSetRef>
        <spirit:fileSetRef>
          <spirit:localName>xilinx_elaboratebd_xilinx_com_ip_shell_utils_cudma_controller_1_0__ref_view_fileset</spirit:localName>
        </spirit:fileSetRef>
        <spirit:fileSetRef>
          <spirit:localName>xilinx_elaboratebd_xilinx_com_ip_shell_utils_kdma_2_0__ref_view_fileset</spirit:localName>
        </spirit:fileSetRef>
        <spirit:fileSetRef>
          <spirit:localName>xilinx_elaboratebd_xilinx_com_ip_shell_utils_cuisr_1_0__ref_view_fileset</spirit:localName>
        </spirit:fileSetRef>
        <spirit:fileSetRef>
          <spirit:localName>xilinx_elaboratebd_xilinx_com_ip_blk_mem_gen_8_4__ref_view_fileset</spirit:localName>
        </spirit:fileSetRef>
        <spirit:fileSetRef>
          <spirit:localName>xilinx_elaboratebd_xilinx_com_ip_axi_intc_4_1__ref_view_fileset</spirit:localName>
        </spirit:fileSetRef>
        <spirit:fileSetRef>
          <spirit:localName>xilinx_elaboratebd_xilinx_com_ip_axi_interconnect_2_1__ref_view_fileset</spirit:localName>
        </spirit:fileSetRef>
        <spirit:fileSetRef>
          <spirit:localName>xilinx_elaboratebd_xilinx_com_ip_axi_clock_converter_2_1__ref_view_fileset</spirit:localName>
        </spirit:fileSetRef>
        <spirit:fileSetRef>
          <spirit:localName>xilinx_elaboratebd_xilinx_com_ip_axi_mmu_2_1__ref_view_fileset</spirit:localName>
        </spirit:fileSetRef>
        <spirit:fileSetRef>
          <spirit:localName>xilinx_elaboratebd_xilinx_com_ip_axi_crossbar_2_1__ref_view_fileset</spirit:localName>
        </spirit:fileSetRef>
        <spirit:fileSetRef>
          <spirit:localName>xilinx_elaboratebd_xilinx_com_ip_axi_bram_ctrl_4_1__ref_view_fileset</spirit:localName>
        </spirit:fileSetRef>
        <spirit:fileSetRef>
          <spirit:localName>xilinx_elaboratebd_xilinx_com_ip_axi_gpio_2_0__ref_view_fileset</spirit:localName>
        </spirit:fileSetRef>
        <spirit:fileSetRef>
          <spirit:localName>xilinx_elaboratebd_xilinx_com_ip_axi_timebase_wdt_3_0__ref_view_fileset</spirit:localName>
        </spirit:fileSetRef>
        <spirit:fileSetRef>
          <spirit:localName>xilinx_elaboratebd_xilinx_com_ip_microblaze_11_0__ref_view_fileset</spirit:localName>
        </spirit:fileSetRef>
        <spirit:fileSetRef>
          <spirit:localName>xilinx_elaboratebd_xilinx_com_ip_proc_sys_reset_5_0__ref_view_fileset</spirit:localName>
        </spirit:fileSetRef>
        <spirit:fileSetRef>
          <spirit:localName>xilinx_elaboratebd_xilinx_com_ip_shell_utils_embedded_scheduler_hw_1_1__ref_view_fileset</spirit:localName>
        </spirit:fileSetRef>
        <spirit:fileSetRef>
          <spirit:localName>xilinx_elaboratebd_xilinx_com_ip_shell_utils_build_info_1_0__ref_view_fileset</spirit:localName>
        </spirit:fileSetRef>
        <spirit:fileSetRef>
          <spirit:localName>xilinx_elaboratebd_xilinx_com_ip_xlconcat_2_1__ref_view_fileset</spirit:localName>
        </spirit:fileSetRef>
        <spirit:fileSetRef>
          <spirit:localName>xilinx_elaboratebd_xilinx_com_ip_lmb_v10_3_0__ref_view_fileset</spirit:localName>
        </spirit:fileSetRef>
        <spirit:fileSetRef>
          <spirit:localName>xilinx_elaboratebd_xilinx_com_ip_lmb_bram_if_cntlr_4_0__ref_view_fileset</spirit:localName>
        </spirit:fileSetRef>
        <spirit:fileSetRef>
          <spirit:localName>xilinx_elaboratebd_xilinx_com_ip_axi_vip_1_1__ref_view_fileset</spirit:localName>
        </spirit:fileSetRef>
        <spirit:fileSetRef>
          <spirit:localName>xilinx_elaboratebd_xilinx_com_ip_xlconstant_1_1__ref_view_fileset</spirit:localName>
        </spirit:fileSetRef>
        <spirit:fileSetRef>
          <spirit:localName>xilinx_elaboratebd_view_fileset</spirit:localName>
        </spirit:fileSetRef>
        <spirit:parameters>
          <spirit:parameter>
            <spirit:name>viewChecksum</spirit:name>
            <spirit:value>818cb41d</spirit:value>
          </spirit:parameter>
        </spirit:parameters>
      </spirit:view>
      <spirit:view>
        <spirit:name>xilinx_elaborateports</spirit:name>
        <spirit:displayName>Elaborate Ports</spirit:displayName>
        <spirit:envIdentifier>:vivado.xilinx.com:elaborate.ports</spirit:envIdentifier>
        <spirit:fileSetRef>
          <spirit:localName>xilinx_elaborateports_view_fileset</spirit:localName>
        </spirit:fileSetRef>
        <spirit:parameters>
          <spirit:parameter>
            <spirit:name>viewChecksum</spirit:name>
            <spirit:value>457fb20c</spirit:value>
          </spirit:parameter>
        </spirit:parameters>
      </spirit:view>
      <spirit:view>
        <spirit:name>xilinx_xpgui</spirit:name>
        <spirit:displayName>UI Layout</spirit:displayName>
        <spirit:envIdentifier>:vivado.xilinx.com:xgui.ui</spirit:envIdentifier>
        <spirit:fileSetRef>
          <spirit:localName>xilinx_xpgui_view_fileset</spirit:localName>
        </spirit:fileSetRef>
        <spirit:parameters>
          <spirit:parameter>
            <spirit:name>viewChecksum</spirit:name>
            <spirit:value>333bacbc</spirit:value>
          </spirit:parameter>
        </spirit:parameters>
      </spirit:view>
      <spirit:view>
        <spirit:name>xilinx_anylanguagebehavioralsimulation</spirit:name>
        <spirit:displayName>Simulation</spirit:displayName>
        <spirit:envIdentifier>:vivado.xilinx.com:simulation</spirit:envIdentifier>
        <spirit:modelName>shell_ert_subsystem_v2_0_0</spirit:modelName>
      </spirit:view>
      <spirit:view>
        <spirit:name>xilinx_anylanguagesynthesis</spirit:name>
        <spirit:displayName>Synthesis</spirit:displayName>
        <spirit:envIdentifier>:vivado.xilinx.com:synthesis</spirit:envIdentifier>
        <spirit:modelName>shell_ert_subsystem_v2_0_0</spirit:modelName>
        <spirit:fileSetRef>
          <spirit:localName>xilinx_anylanguagesynthesis_view_fileset</spirit:localName>
        </spirit:fileSetRef>
        <spirit:parameters>
          <spirit:parameter>
            <spirit:name>viewChecksum</spirit:name>
            <spirit:value>d9ed3c9b</spirit:value>
          </spirit:parameter>
        </spirit:parameters>
      </spirit:view>
      <spirit:view>
        <spirit:name>xilinx_utilityxitfiles</spirit:name>
        <spirit:displayName>Utility XIT/TTCL</spirit:displayName>
        <spirit:envIdentifier>:vivado.xilinx.com:xit.util</spirit:envIdentifier>
        <spirit:fileSetRef>
          <spirit:localName>xilinx_utilityxitfiles_view_fileset</spirit:localName>
        </spirit:fileSetRef>
        <spirit:parameters>
          <spirit:parameter>
            <spirit:name>viewChecksum</spirit:name>
            <spirit:value>ae1127d4</spirit:value>
          </spirit:parameter>
        </spirit:parameters>
      </spirit:view>
      <spirit:view>
        <spirit:name>xilinx_versioninformation</spirit:name>
        <spirit:displayName>Version Information</spirit:displayName>
        <spirit:envIdentifier>:vivado.xilinx.com:docs.versioninfo</spirit:envIdentifier>
        <spirit:fileSetRef>
          <spirit:localName>xilinx_versioninformation_view_fileset</spirit:localName>
        </spirit:fileSetRef>
      </spirit:view>
    </spirit:views>
  </spirit:model>
  <spirit:choices>
    <spirit:choice>
      <spirit:name>choice_list_9b94c6ac</spirit:name>
      <spirit:enumeration>4k</spirit:enumeration>
      <spirit:enumeration>8k</spirit:enumeration>
      <spirit:enumeration>16k</spirit:enumeration>
      <spirit:enumeration>32k</spirit:enumeration>
      <spirit:enumeration>64k</spirit:enumeration>
      <spirit:enumeration>128k</spirit:enumeration>
      <spirit:enumeration>256k</spirit:enumeration>
    </spirit:choice>
    <spirit:choice>
      <spirit:name>choice_list_ce018cf7</spirit:name>
      <spirit:enumeration>Gen3x4</spirit:enumeration>
      <spirit:enumeration>Gen3x8</spirit:enumeration>
      <spirit:enumeration>Gen3x16</spirit:enumeration>
    </spirit:choice>
  </spirit:choices>
  <spirit:fileSets>
    <spirit:fileSet>
      <spirit:name>xilinx_blockdiagram_view_fileset</spirit:name>
      <spirit:file>
        <spirit:name>bd/bd.tcl</spirit:name>
        <spirit:fileType>tclSource</spirit:fileType>
      </spirit:file>
    </spirit:fileSet>
    <spirit:fileSet>
      <spirit:name>xilinx_elaboratebd_view_fileset</spirit:name>
      <spirit:file>
        <spirit:name>xit/update_contents.xit</spirit:name>
        <spirit:userFileType>xit</spirit:userFileType>
      </spirit:file>
    </spirit:fileSet>
    <spirit:fileSet>
      <spirit:name>xilinx_elaboratebd_xilinx_com_ip_axi_protocol_converter_2_1__ref_view_fileset</spirit:name>
      <spirit:vendorExtensions>
        <xilinx:subCoreRef>
          <xilinx:componentRef xsi:type="xilinx:componentRefType" xilinx:vendor="xilinx.com" xilinx:library="ip" xilinx:name="axi_protocol_converter" xilinx:version="2.1" xilinx:coreRevision="20">
            <xilinx:mode xilinx:name="create_mode"/>
          </xilinx:componentRef>
        </xilinx:subCoreRef>
      </spirit:vendorExtensions>
    </spirit:fileSet>
    <spirit:fileSet>
      <spirit:name>xilinx_elaboratebd_xilinx_com_ip_shell_utils_cudma_controller_1_0__ref_view_fileset</spirit:name>
      <spirit:vendorExtensions>
        <xilinx:subCoreRef>
          <xilinx:componentRef xilinx:vendor="xilinx.com" xilinx:library="ip" xilinx:name="shell_utils_cudma_controller" xilinx:version="1.0" xilinx:coreRevision="0">
            <xilinx:mode xilinx:name="create_mode"/>
          </xilinx:componentRef>
        </xilinx:subCoreRef>
      </spirit:vendorExtensions>
    </spirit:fileSet>
    <spirit:fileSet>
      <spirit:name>xilinx_elaboratebd_xilinx_com_ip_shell_utils_kdma_2_0__ref_view_fileset</spirit:name>
      <spirit:vendorExtensions>
        <xilinx:subCoreRef>
          <xilinx:componentRef xilinx:vendor="xilinx.com" xilinx:library="ip" xilinx:name="shell_utils_kdma" xilinx:version="2.0" xilinx:coreRevision="0">
            <xilinx:mode xilinx:name="create_mode"/>
          </xilinx:componentRef>
        </xilinx:subCoreRef>
      </spirit:vendorExtensions>
    </spirit:fileSet>
    <spirit:fileSet>
      <spirit:name>xilinx_elaboratebd_xilinx_com_ip_shell_utils_cuisr_1_0__ref_view_fileset</spirit:name>
      <spirit:vendorExtensions>
        <xilinx:subCoreRef>
          <xilinx:componentRef xilinx:vendor="xilinx.com" xilinx:library="ip" xilinx:name="shell_utils_cuisr" xilinx:version="1.0" xilinx:coreRevision="0">
            <xilinx:mode xilinx:name="create_mode"/>
          </xilinx:componentRef>
        </xilinx:subCoreRef>
      </spirit:vendorExtensions>
    </spirit:fileSet>
    <spirit:fileSet>
      <spirit:name>xilinx_elaboratebd_xilinx_com_ip_blk_mem_gen_8_4__ref_view_fileset</spirit:name>
      <spirit:vendorExtensions>
        <xilinx:subCoreRef>
          <xilinx:componentRef xilinx:vendor="xilinx.com" xilinx:library="ip" xilinx:name="blk_mem_gen" xilinx:version="8.4" xilinx:coreRevision="4">
            <xilinx:mode xilinx:name="create_mode"/>
          </xilinx:componentRef>
        </xilinx:subCoreRef>
      </spirit:vendorExtensions>
    </spirit:fileSet>
    <spirit:fileSet>
      <spirit:name>xilinx_elaboratebd_xilinx_com_ip_axi_intc_4_1__ref_view_fileset</spirit:name>
      <spirit:vendorExtensions>
        <xilinx:subCoreRef>
          <xilinx:componentRef xilinx:vendor="xilinx.com" xilinx:library="ip" xilinx:name="axi_intc" xilinx:version="4.1" xilinx:coreRevision="14">
            <xilinx:mode xilinx:name="create_mode"/>
          </xilinx:componentRef>
        </xilinx:subCoreRef>
      </spirit:vendorExtensions>
    </spirit:fileSet>
    <spirit:fileSet>
      <spirit:name>xilinx_elaboratebd_xilinx_com_ip_axi_interconnect_2_1__ref_view_fileset</spirit:name>
      <spirit:vendorExtensions>
        <xilinx:subCoreRef>
          <xilinx:componentRef xilinx:vendor="xilinx.com" xilinx:library="ip" xilinx:name="axi_interconnect" xilinx:version="2.1" xilinx:coreRevision="21">
            <xilinx:mode xilinx:name="create_mode"/>
          </xilinx:componentRef>
        </xilinx:subCoreRef>
      </spirit:vendorExtensions>
    </spirit:fileSet>
    <spirit:fileSet>
      <spirit:name>xilinx_elaboratebd_xilinx_com_ip_axi_clock_converter_2_1__ref_view_fileset</spirit:name>
      <spirit:vendorExtensions>
        <xilinx:subCoreRef>
          <xilinx:componentRef xilinx:vendor="xilinx.com" xilinx:library="ip" xilinx:name="axi_clock_converter" xilinx:version="2.1" xilinx:coreRevision="19">
            <xilinx:mode xilinx:name="create_mode"/>
          </xilinx:componentRef>
        </xilinx:subCoreRef>
      </spirit:vendorExtensions>
    </spirit:fileSet>
    <spirit:fileSet>
      <spirit:name>xilinx_elaboratebd_xilinx_com_ip_axi_mmu_2_1__ref_view_fileset</spirit:name>
      <spirit:vendorExtensions>
        <xilinx:subCoreRef>
          <xilinx:componentRef xilinx:vendor="xilinx.com" xilinx:library="ip" xilinx:name="axi_mmu" xilinx:version="2.1" xilinx:coreRevision="18">
            <xilinx:mode xilinx:name="create_mode"/>
          </xilinx:componentRef>
        </xilinx:subCoreRef>
      </spirit:vendorExtensions>
    </spirit:fileSet>
    <spirit:fileSet>
      <spirit:name>xilinx_elaboratebd_xilinx_com_ip_axi_crossbar_2_1__ref_view_fileset</spirit:name>
      <spirit:vendorExtensions>
        <xilinx:subCoreRef>
          <xilinx:componentRef xilinx:vendor="xilinx.com" xilinx:library="ip" xilinx:name="axi_crossbar" xilinx:version="2.1" xilinx:coreRevision="21">
            <xilinx:mode xilinx:name="create_mode"/>
          </xilinx:componentRef>
        </xilinx:subCoreRef>
      </spirit:vendorExtensions>
    </spirit:fileSet>
    <spirit:fileSet>
      <spirit:name>xilinx_elaboratebd_xilinx_com_ip_axi_bram_ctrl_4_1__ref_view_fileset</spirit:name>
      <spirit:vendorExtensions>
        <xilinx:subCoreRef>
          <xilinx:componentRef xilinx:vendor="xilinx.com" xilinx:library="ip" xilinx:name="axi_bram_ctrl" xilinx:version="4.1" xilinx:coreRevision="2">
            <xilinx:mode xilinx:name="create_mode"/>
          </xilinx:componentRef>
        </xilinx:subCoreRef>
      </spirit:vendorExtensions>
    </spirit:fileSet>
    <spirit:fileSet>
      <spirit:name>xilinx_elaboratebd_xilinx_com_ip_axi_gpio_2_0__ref_view_fileset</spirit:name>
      <spirit:vendorExtensions>
        <xilinx:subCoreRef>
          <xilinx:componentRef xilinx:vendor="xilinx.com" xilinx:library="ip" xilinx:name="axi_gpio" xilinx:version="2.0" xilinx:coreRevision="22">
            <xilinx:mode xilinx:name="create_mode"/>
          </xilinx:componentRef>
        </xilinx:subCoreRef>
      </spirit:vendorExtensions>
    </spirit:fileSet>
    <spirit:fileSet>
      <spirit:name>xilinx_elaboratebd_xilinx_com_ip_axi_timebase_wdt_3_0__ref_view_fileset</spirit:name>
      <spirit:vendorExtensions>
        <xilinx:subCoreRef>
          <xilinx:componentRef xilinx:vendor="xilinx.com" xilinx:library="ip" xilinx:name="axi_timebase_wdt" xilinx:version="3.0" xilinx:coreRevision="12">
            <xilinx:mode xilinx:name="create_mode"/>
          </xilinx:componentRef>
        </xilinx:subCoreRef>
      </spirit:vendorExtensions>
    </spirit:fileSet>
    <spirit:fileSet>
      <spirit:name>xilinx_elaboratebd_xilinx_com_ip_microblaze_11_0__ref_view_fileset</spirit:name>
      <spirit:vendorExtensions>
        <xilinx:subCoreRef>
          <xilinx:componentRef xilinx:vendor="xilinx.com" xilinx:library="ip" xilinx:name="microblaze" xilinx:version="11.0" xilinx:coreRevision="2">
            <xilinx:mode xilinx:name="create_mode"/>
          </xilinx:componentRef>
        </xilinx:subCoreRef>
      </spirit:vendorExtensions>
    </spirit:fileSet>
    <spirit:fileSet>
      <spirit:name>xilinx_elaboratebd_xilinx_com_ip_proc_sys_reset_5_0__ref_view_fileset</spirit:name>
      <spirit:vendorExtensions>
        <xilinx:subCoreRef>
          <xilinx:componentRef xilinx:vendor="xilinx.com" xilinx:library="ip" xilinx:name="proc_sys_reset" xilinx:version="5.0" xilinx:coreRevision="13">
            <xilinx:mode xilinx:name="create_mode"/>
          </xilinx:componentRef>
        </xilinx:subCoreRef>
      </spirit:vendorExtensions>
    </spirit:fileSet>
    <spirit:fileSet>
      <spirit:name>xilinx_elaboratebd_xilinx_com_ip_shell_utils_embedded_scheduler_hw_1_1__ref_view_fileset</spirit:name>
      <spirit:vendorExtensions>
        <xilinx:subCoreRef>
          <xilinx:componentRef xilinx:vendor="xilinx.com" xilinx:library="ip" xilinx:name="shell_utils_embedded_scheduler_hw" xilinx:version="1.1" xilinx:coreRevision="0">
            <xilinx:mode xilinx:name="create_mode"/>
          </xilinx:componentRef>
        </xilinx:subCoreRef>
      </spirit:vendorExtensions>
    </spirit:fileSet>
    <spirit:fileSet>
      <spirit:name>xilinx_elaboratebd_xilinx_com_ip_shell_utils_build_info_1_0__ref_view_fileset</spirit:name>
      <spirit:vendorExtensions>
        <xilinx:subCoreRef>
          <xilinx:componentRef xilinx:vendor="xilinx.com" xilinx:library="ip" xilinx:name="shell_utils_build_info" xilinx:version="1.0" xilinx:coreRevision="0">
            <xilinx:mode xilinx:name="create_mode"/>
          </xilinx:componentRef>
        </xilinx:subCoreRef>
      </spirit:vendorExtensions>
    </spirit:fileSet>
    <spirit:fileSet>
      <spirit:name>xilinx_elaboratebd_xilinx_com_ip_xlconcat_2_1__ref_view_fileset</spirit:name>
      <spirit:vendorExtensions>
        <xilinx:subCoreRef>
          <xilinx:componentRef xilinx:vendor="xilinx.com" xilinx:library="ip" xilinx:name="xlconcat" xilinx:version="2.1" xilinx:coreRevision="3">
            <xilinx:mode xilinx:name="create_mode"/>
          </xilinx:componentRef>
        </xilinx:subCoreRef>
      </spirit:vendorExtensions>
    </spirit:fileSet>
    <spirit:fileSet>
      <spirit:name>xilinx_elaboratebd_xilinx_com_ip_lmb_v10_3_0__ref_view_fileset</spirit:name>
      <spirit:vendorExtensions>
        <xilinx:subCoreRef>
          <xilinx:componentRef xilinx:vendor="xilinx.com" xilinx:library="ip" xilinx:name="lmb_v10" xilinx:version="3.0" xilinx:coreRevision="10">
            <xilinx:mode xilinx:name="create_mode"/>
          </xilinx:componentRef>
        </xilinx:subCoreRef>
      </spirit:vendorExtensions>
    </spirit:fileSet>
    <spirit:fileSet>
      <spirit:name>xilinx_elaboratebd_xilinx_com_ip_lmb_bram_if_cntlr_4_0__ref_view_fileset</spirit:name>
      <spirit:vendorExtensions>
        <xilinx:subCoreRef>
          <xilinx:componentRef xilinx:vendor="xilinx.com" xilinx:library="ip" xilinx:name="lmb_bram_if_cntlr" xilinx:version="4.0" xilinx:coreRevision="17">
            <xilinx:mode xilinx:name="create_mode"/>
          </xilinx:componentRef>
        </xilinx:subCoreRef>
      </spirit:vendorExtensions>
    </spirit:fileSet>
    <spirit:fileSet>
      <spirit:name>xilinx_elaboratebd_xilinx_com_ip_axi_vip_1_1__ref_view_fileset</spirit:name>
      <spirit:vendorExtensions>
        <xilinx:subCoreRef>
          <xilinx:componentRef xilinx:vendor="xilinx.com" xilinx:library="ip" xilinx:name="axi_vip" xilinx:version="1.1" xilinx:coreRevision="6">
            <xilinx:mode xilinx:name="create_mode"/>
          </xilinx:componentRef>
        </xilinx:subCoreRef>
      </spirit:vendorExtensions>
    </spirit:fileSet>
    <spirit:fileSet>
      <spirit:name>xilinx_elaboratebd_xilinx_com_ip_xlconstant_1_1__ref_view_fileset</spirit:name>
      <spirit:vendorExtensions>
        <xilinx:subCoreRef>
          <xilinx:componentRef xilinx:vendor="xilinx.com" xilinx:library="ip" xilinx:name="xlconstant" xilinx:version="1.1" xilinx:coreRevision="6">
            <xilinx:mode xilinx:name="create_mode"/>
          </xilinx:componentRef>
        </xilinx:subCoreRef>
      </spirit:vendorExtensions>
    </spirit:fileSet>
    <spirit:fileSet>
      <spirit:name>xilinx_elaborateports_view_fileset</spirit:name>
      <spirit:file>
        <spirit:name>xit/update_ports.xit</spirit:name>
        <spirit:userFileType>xit</spirit:userFileType>
      </spirit:file>
    </spirit:fileSet>
    <spirit:fileSet>
      <spirit:name>xilinx_xpgui_view_fileset</spirit:name>
      <spirit:file>
        <spirit:name>xgui/shell_ert_subsystem_v2_0.tcl</spirit:name>
        <spirit:fileType>tclSource</spirit:fileType>
        <spirit:userFileType>XGUI_VERSION_2</spirit:userFileType>
      </spirit:file>
    </spirit:fileSet>
    <spirit:fileSet>
      <spirit:name>xilinx_anylanguagesynthesis_view_fileset</spirit:name>
      <spirit:file>
        <spirit:name>ttcl/utils/common.ttcl</spirit:name>
        <spirit:userFileType>ttcl</spirit:userFileType>
      </spirit:file>
      <spirit:file>
        <spirit:name>ttcl/xdc/ooc_xdc.ttcl</spirit:name>
        <spirit:userFileType>ttcl</spirit:userFileType>
      </spirit:file>
      <spirit:file>
        <spirit:name>ttcl/utils/disclaimer.ttcl</spirit:name>
        <spirit:userFileType>ttcl</spirit:userFileType>
      </spirit:file>
    </spirit:fileSet>
    <spirit:fileSet>
      <spirit:name>xilinx_utilityxitfiles_view_fileset</spirit:name>
      <spirit:file>
        <spirit:name>xit/get_params.xit</spirit:name>
        <spirit:userFileType>xit</spirit:userFileType>
      </spirit:file>
      <spirit:file>
        <spirit:name>xit/util.xit</spirit:name>
        <spirit:userFileType>xit</spirit:userFileType>
      </spirit:file>
      <spirit:file>
        <spirit:name>xit/debug_util.xit</spirit:name>
        <spirit:userFileType>xit</spirit:userFileType>
      </spirit:file>
      <spirit:file>
        <spirit:name>xit/generate_ports.xit</spirit:name>
        <spirit:userFileType>xit</spirit:userFileType>
      </spirit:file>
      <spirit:file>
        <spirit:name>xit/generate_contents.xit</spirit:name>
        <spirit:userFileType>xit</spirit:userFileType>
      </spirit:file>
    </spirit:fileSet>
    <spirit:fileSet>
      <spirit:name>xilinx_versioninformation_view_fileset</spirit:name>
      <spirit:file>
        <spirit:name>doc/shell_ert_subsystem_v2_0_changelog.txt</spirit:name>
        <spirit:userFileType>text</spirit:userFileType>
      </spirit:file>
    </spirit:fileSet>
  </spirit:fileSets>
  <spirit:description>Shell Subsystem - ERT</spirit:description>
  <spirit:parameters>
    <spirit:parameter>
      <spirit:name>Component_Name</spirit:name>
      <spirit:value spirit:resolve="user" spirit:id="PARAM_VALUE.Component_Name" spirit:order="2">shell_ert_subsystem_v2_0</spirit:value>
      <spirit:vendorExtensions>
        <xilinx:parameterInfo>
          <xilinx:enablement>
            <xilinx:isEnabled xilinx:resolve="dependent" xilinx:id="PARAM_ENABLEMENT.Component_Name">true</xilinx:isEnabled>
          </xilinx:enablement>
        </xilinx:parameterInfo>
      </spirit:vendorExtensions>
    </spirit:parameter>
    <spirit:parameter>
      <spirit:name>VERSION.SUBSYSTEM_ID</spirit:name>
      <spirit:displayName>Subsystem ID</spirit:displayName>
      <spirit:value spirit:format="bitString" spirit:resolve="user" spirit:id="PARAM_VALUE.VERSION.SUBSYSTEM_ID" spirit:order="3" spirit:bitStringLength="8">0x05</spirit:value>
      <spirit:vendorExtensions>
        <xilinx:parameterInfo>
          <xilinx:enablement>
            <xilinx:isEnabled xilinx:id="PARAM_ENABLEMENT.VERSION.SUBSYSTEM_ID">false</xilinx:isEnabled>
          </xilinx:enablement>
        </xilinx:parameterInfo>
      </spirit:vendorExtensions>
    </spirit:parameter>
    <spirit:parameter>
      <spirit:name>VERSION.VIV_VERSION</spirit:name>
      <spirit:displayName>Target Vivado Tool Version</spirit:displayName>
      <spirit:value spirit:format="bitString" spirit:resolve="user" spirit:id="PARAM_VALUE.VERSION.VIV_VERSION" spirit:order="4" spirit:bitStringLength="24">0x201920</spirit:value>
      <spirit:vendorExtensions>
        <xilinx:parameterInfo>
          <xilinx:enablement>
            <xilinx:isEnabled xilinx:id="PARAM_ENABLEMENT.VERSION.VIV_VERSION">false</xilinx:isEnabled>
          </xilinx:enablement>
        </xilinx:parameterInfo>
      </spirit:vendorExtensions>
    </spirit:parameter>
    <spirit:parameter>
      <spirit:name>VERSION.MAJOR_VERSION</spirit:name>
      <spirit:displayName>Subsystem Major Version</spirit:displayName>
      <spirit:value spirit:format="long" spirit:resolve="user" spirit:id="PARAM_VALUE.VERSION.MAJOR_VERSION" spirit:order="5">0</spirit:value>
    </spirit:parameter>
    <spirit:parameter>
      <spirit:name>VERSION.MINOR_VERSION</spirit:name>
      <spirit:displayName>Subsystem Minor Version</spirit:displayName>
      <spirit:value spirit:format="long" spirit:resolve="user" spirit:id="PARAM_VALUE.VERSION.MINOR_VERSION" spirit:order="6">0</spirit:value>
    </spirit:parameter>
    <spirit:parameter>
      <spirit:name>VERSION.CORE_REVISION</spirit:name>
      <spirit:displayName>Subsystem Core Revision</spirit:displayName>
      <spirit:value spirit:format="long" spirit:resolve="user" spirit:id="PARAM_VALUE.VERSION.CORE_REVISION" spirit:order="7">0</spirit:value>
    </spirit:parameter>
    <spirit:parameter>
      <spirit:name>VERSION.PATCH_REVISION</spirit:name>
      <spirit:displayName>Subsystem Patch Revision</spirit:displayName>
      <spirit:value spirit:format="long" spirit:resolve="user" spirit:id="PARAM_VALUE.VERSION.PATCH_REVISION" spirit:order="8">0</spirit:value>
    </spirit:parameter>
    <spirit:parameter>
      <spirit:name>VERSION.RESERVED_TAG</spirit:name>
      <spirit:displayName>Reserved Tag</spirit:displayName>
      <spirit:value spirit:format="bitString" spirit:resolve="user" spirit:id="PARAM_VALUE.VERSION.RESERVED_TAG" spirit:order="9" spirit:bitStringLength="32">0x00000000</spirit:value>
      <spirit:vendorExtensions>
        <xilinx:parameterInfo>
          <xilinx:enablement>
            <xilinx:isEnabled xilinx:id="PARAM_ENABLEMENT.VERSION.RESERVED_TAG">false</xilinx:isEnabled>
          </xilinx:enablement>
        </xilinx:parameterInfo>
      </spirit:vendorExtensions>
    </spirit:parameter>
    <spirit:parameter>
      <spirit:name>RANGE_CQ_BRAM_CTRL_SEG</spirit:name>
      <spirit:displayName>CQ_BRAM_CTRL range</spirit:displayName>
      <spirit:value spirit:resolve="user" spirit:id="PARAM_VALUE.RANGE_CQ_BRAM_CTRL_SEG" spirit:choiceRef="choice_list_9b94c6ac" spirit:order="10">64k</spirit:value>
    </spirit:parameter>
    <spirit:parameter>
      <spirit:name>RANGE_AXI_BRAM_CTRL_LMB_SEG</spirit:name>
      <spirit:displayName>AXI_BRAM_CTRL_LMB range</spirit:displayName>
      <spirit:value spirit:resolve="user" spirit:id="PARAM_VALUE.RANGE_AXI_BRAM_CTRL_LMB_SEG" spirit:choiceRef="choice_list_9b94c6ac" spirit:order="11">32k</spirit:value>
    </spirit:parameter>
    <spirit:parameter>
      <spirit:name>MB_BASE_VECTORS</spirit:name>
      <spirit:displayName>Microblaze Base Vector Address</spirit:displayName>
      <spirit:value spirit:format="bitString" spirit:resolve="user" spirit:id="PARAM_VALUE.MB_BASE_VECTORS" spirit:order="12" spirit:bitStringLength="32">0xF0000000</spirit:value>
    </spirit:parameter>
    <spirit:parameter>
      <spirit:name>REMOVE_KDMA</spirit:name>
      <spirit:displayName>Remove KDMA</spirit:displayName>
      <spirit:value spirit:format="bool" spirit:resolve="user" spirit:id="PARAM_VALUE.REMOVE_KDMA" spirit:order="13">false</spirit:value>
      <spirit:vendorExtensions>
        <xilinx:parameterInfo>
          <xilinx:enablement>
            <xilinx:isEnabled xilinx:resolve="dependent" xilinx:id="PARAM_ENABLEMENT.REMOVE_KDMA">true</xilinx:isEnabled>
          </xilinx:enablement>
        </xilinx:parameterInfo>
      </spirit:vendorExtensions>
    </spirit:parameter>
    <spirit:parameter>
      <spirit:name>PCIE_LINK_CAP_MAX</spirit:name>
      <spirit:displayName>Link Width Capability</spirit:displayName>
      <spirit:value spirit:resolve="user" spirit:id="PARAM_VALUE.PCIE_LINK_CAP_MAX" spirit:choiceRef="choice_list_ce018cf7" spirit:order="14">Gen3x16</spirit:value>
      <spirit:vendorExtensions>
        <xilinx:parameterInfo>
          <xilinx:enablement>
            <xilinx:isEnabled xilinx:resolve="dependent" xilinx:id="PARAM_ENABLEMENT.PCIE_LINK_CAP_MAX" xilinx:dependency="spirit:decode(id(&apos;PARAM_VALUE.REMOVE_KDMA&apos;)) = FALSE">true</xilinx:isEnabled>
          </xilinx:enablement>
        </xilinx:parameterInfo>
      </spirit:vendorExtensions>
    </spirit:parameter>
    <spirit:parameter>
      <spirit:name>ERT_MGMT_PF_BASE_ADDR</spirit:name>
      <spirit:displayName>ERT Subsystem MGMT PF Base Address</spirit:displayName>
      <spirit:value spirit:format="bitString" spirit:resolve="user" spirit:id="PARAM_VALUE.ERT_MGMT_PF_BASE_ADDR" spirit:order="15" spirit:bitStringLength="32">0x00020000</spirit:value>
    </spirit:parameter>
    <spirit:parameter>
      <spirit:name>ERT_USER_PF_BASE_ADDR</spirit:name>
      <spirit:displayName>ERT Subsystem USER PF Base Address</spirit:displayName>
      <spirit:value spirit:format="bitString" spirit:resolve="user" spirit:id="PARAM_VALUE.ERT_USER_PF_BASE_ADDR" spirit:order="16" spirit:bitStringLength="32">0x00040000</spirit:value>
    </spirit:parameter>
    <spirit:parameter>
      <spirit:name>VERSION.PERFORCE_CL</spirit:name>
      <spirit:displayName>VERSION.PERFORCE_CL</spirit:displayName>
      <spirit:value spirit:format="long" spirit:resolve="user" spirit:id="PARAM_VALUE.VERSION.PERFORCE_CL">2767516</spirit:value>
      <spirit:vendorExtensions>
        <xilinx:parameterInfo>
          <xilinx:enablement>
            <xilinx:isEnabled xilinx:id="PARAM_ENABLEMENT.VERSION.PERFORCE_CL">false</xilinx:isEnabled>
          </xilinx:enablement>
        </xilinx:parameterInfo>
      </spirit:vendorExtensions>
    </spirit:parameter>
  </spirit:parameters>
  <spirit:vendorExtensions>
    <xilinx:coreExtensions>
      <xilinx:supportedFamilies>
        <xilinx:family xilinx:lifeCycle="Production">virtexuplusHBM{xcu(50|280)-(.*)-(.*)-(.*)}</xilinx:family>
        <xilinx:family xilinx:lifeCycle="Production">virtexuplusHBM{xcvu35p-(.*)-(.*)-(.*)}</xilinx:family>
        <xilinx:family xilinx:lifeCycle="Production">virtexuplus{xcu(200|250)-(.*)-(.*)-(.*)}</xilinx:family>
        <xilinx:family xilinx:lifeCycle="Production">virtexuplus{xcvu9p-(.*)-(.*)-(.*)}</xilinx:family>
        <xilinx:family xilinx:lifeCycle="Beta">zynquplus{xcu(25|30)-(.*)-(.*)-(.*)}</xilinx:family>
      </xilinx:supportedFamilies>
      <xilinx:taxonomies>
        <xilinx:taxonomy>/Shell_Subsystems</xilinx:taxonomy>
      </xilinx:taxonomies>
      <xilinx:displayName>Shell Embedded Runtime Subsystem</xilinx:displayName>
      <xilinx:designToolContexts>
        <xilinx:designToolContext>IPI</xilinx:designToolContext>
      </xilinx:designToolContexts>
      <xilinx:coreRevision>0</xilinx:coreRevision>
      <xilinx:coreCreationDateTime>2020-01-31T16:48:51Z</xilinx:coreCreationDateTime>
    </xilinx:coreExtensions>
    <xilinx:packagingInfo>
      <xilinx:xilinxVersion>2019.2</xilinx:xilinxVersion>
      <xilinx:checksum xilinx:scope="fileGroups" xilinx:value="cd09b002"/>
      <xilinx:checksum xilinx:scope="parameters" xilinx:value="24c25262"/>
    </xilinx:packagingInfo>
  </spirit:vendorExtensions>
</spirit:component>
